Metadata-Version: 2.1
Name: adamgpppythoncodestorage
Version: 0.0.4
Summary: Private Python Code Storage
Home-page: https://github.com/adamgpp/python_storage
Author: Adam Guła
Author-email: nacoipoco@gmail.com
License: UNKNOWN
Platform: UNKNOWN
Classifier: Programming Language :: Python :: 3
Classifier: License :: OSI Approved :: MIT License
Classifier: Operating System :: OS Independent
